blanc_admin_theme/__init__.py
blanc_admin_theme/static/admin/css/base.css
blanc_admin_theme/static/admin/css/base.less
blanc_admin_theme/static/admin/css/changelists.css
blanc_admin_theme/static/admin/css/changelists.less
blanc_admin_theme/static/admin/css/fonts.css
blanc_admin_theme/static/admin/css/fonts.less
blanc_admin_theme/static/admin/css/forms.css
blanc_admin_theme/static/admin/css/forms.less
blanc_admin_theme/static/admin/css/global.less
blanc_admin_theme/static/admin/css/widgets.css
blanc_admin_theme/static/admin/css/widgets.less
blanc_admin_theme/static/admin/fonts/OFL.txt
blanc_admin_theme/static/admin/fonts/SourceSansPro-Black.ttf
blanc_admin_theme/static/admin/fonts/SourceSansPro-BlackItalic.ttf
blanc_admin_theme/static/admin/fonts/SourceSansPro-Bold.ttf
blanc_admin_theme/static/admin/fonts/SourceSansPro-BoldItalic.ttf
blanc_admin_theme/static/admin/fonts/SourceSansPro-ExtraLight.ttf
blanc_admin_theme/static/admin/fonts/SourceSansPro-ExtraLightItalic.ttf
blanc_admin_theme/static/admin/fonts/SourceSansPro-Italic.ttf
blanc_admin_theme/static/admin/fonts/SourceSansPro-Light.ttf
blanc_admin_theme/static/admin/fonts/SourceSansPro-LightItalic.ttf
blanc_admin_theme/static/admin/fonts/SourceSansPro-Regular.ttf
blanc_admin_theme/static/admin/fonts/SourceSansPro-Semibold.ttf
blanc_admin_theme/static/admin/fonts/SourceSansPro-SemiboldItalic.ttf
blanc_admin_theme/static/admin/img/changelist-bg.gif
blanc_admin_theme/static/admin/img/changelist-bg_rtl.gif
blanc_admin_theme/static/admin/img/default-bg-reverse.gif
blanc_admin_theme/static/admin/img/default-bg.gif
blanc_admin_theme/static/admin/img/deleted-overlay.gif
blanc_admin_theme/static/admin/img/icon-no.gif
blanc_admin_theme/static/admin/img/icon-unknown.gif
blanc_admin_theme/static/admin/img/icon-yes.gif
blanc_admin_theme/static/admin/img/icon_addlink.gif
blanc_admin_theme/static/admin/img/icon_alert.gif
blanc_admin_theme/static/admin/img/icon_calendar.gif
blanc_admin_theme-1.0.2.dist-info/DESCRIPTION.rst
blanc_admin_theme-1.0.2.dist-info/METADATA
blanc_admin_theme-1.0.2.dist-info/RECORD
blanc_admin_theme-1.0.2.dist-info/WHEEL
blanc_admin_theme-1.0.2.dist-info/metadata.json
blanc_admin_theme-1.0.2.dist-info/top_level.txt
