Metadata-Version: 2.0
Name: blanc-admin-theme
Version: 1.0.2
Summary: Blanc's theme for the Django admin.
Home-page: https://github.com/blancltd/blanc-admin-theme
Author: Blanc Ltd
Author-email: studio@blanc.ltd.uk
License: BSD
Keywords: django,admin,theme,interface
Platform: UNKNOWN
